frappymongodataset/__init__.py
frappymongodataset/data_store.py
frappymongodataset/mmacommon.py
frappymongodataset-1.3.3.dist-info/LICENSE
frappymongodataset-1.3.3.dist-info/METADATA
frappymongodataset-1.3.3.dist-info/WHEEL
frappymongodataset-1.3.3.dist-info/top_level.txt
frappymongodataset-1.3.3.dist-info/RECORD
