Metadata-Version: 2.1
Name: frappymongodataset
Version: 1.3.3
Summary: Store Implementation for Data Sets in MongoDB
Home-page: https://github.com/ilfrich/frappy-py-mongo-dataset-store
Author: Peter Ilfrich
Author-email: das-peter@gmx.de
License: UNKNOWN
Platform: UNKNOWN
Requires-Dist: pbumongo (>=1.0.0)
Requires-Dist: numpy
Requires-Dist: Pillow
Requires-Dist: pandas
